{
    "playername": "qzdqz",
    "charactername": "qzdqzd",
    "sex": "dqzdqz",
    "race": "elf",
    "class": "paladin",
    "level": "1",
    "strength": "14",
    "dexterity": "15",
    "constitution": "15",
    "intelligence": "10",
    "wisdom": "8",
    "charisma": "8",
    "alignment": "ln",
    "background": "charlatan",
    "proficiencies": [
        "sleightofhand",
        "deception"
    ],
    "flaw": "dqzq",
    "trait": "dqzdqzd",
    "ideal": "qzdqzdq",
    "bond": "dqzdqz",
    "languages": [
        "common",
        "elvish",
        "gnomish",
        "deep speech"
    ],
    "equipment": "qzdq",
    "ac": 12,
    "age": "242315",
    "eyes": "Afze",
    "hair": "dqdqz",
    "skin": "qfqzd",
    "weight": "qzfqzf",
    "height": "fzfqzfqz",
    "appearance": "fqzf",
    "profsaves": [
        "wisdom",
        "charisma"
    ],
    "profbonus": 2,
    "strmod": 2,
    "dexmod": 2,
    "conmod": 2,
    "intmod": 0,
    "wismod": -1,
    "chamod": -1,
    "hitdice": 10,
    "hp": 12,
    "initiative": 2,
    "speed": 30,
    "traitsabilities": "Traits :\ndarkvision\nkeen senses\nfey ancestry\ntrance\nAbilities:\nDivine Sense\nLay on Hands\n",
    "itemproficiencies": "all armor\nshields\nsimple weapons\nmartial weapons"
}